{
    "GAME_OVER": {
        "skills": [
            "climb"
        ],
        "image": "assets/GAME_OVER.png",
        "initial_msg": "Koniec hry! Chceš hrať ešte raz?",
        "choice_A": "Áno.",
        "case_A": "restart"
    },
    "DISTRACT_PREDATOR": {
        "skills": [
            "throw"
        ],
        "difficulty": 10,
        "threat": 4,
        "image": "assets/WRECKS.png",
        "initial_msg": "Na zemi nájdeš kameň a hodíš ho čo najďalej.",
        "success_msg": "Podarilo sa. Predátorka išla za zvukom.",
        "threat_msg": "Hádzal si kameň a nevšimol si si, kam zmizla. Teraz určite sliedi po okolí a vie, že si tu. Vyskočí na teba zo zálohy.",
        "threat_avoided_msg": "Snažila sa dostať za teba, ale odhalil si jej zámer.",
        "failure_msg": "Odhalila ťa, už jej neujdeš.",
        "case_success": "if_distractBasment:true_CITY_2_else_WRECKS",
        "case_threat": "enemy_advantage+1",
        "case_threat_delayed": "if_distractBasment:true_BASEMENT_PREDATOR_2_else_WRECKS_PREDATOR_2",
        "case_failure": [
            "if_distractBasment:true_CITY_2_else_WRECKS",
            "Predátorka_2"
        ],
        "enemy_escape_delayed": "WRECKS_PREDATOR_2"
    },
    "WRECKS_PREDATOR_2": {
        "image": "assets/WRECKS_PREDATOR.png",
        "initial_msg": "Opäť ťa objavila predátorka.",
        "choice_A": "Odlákať ju kameňom",
        "choice_B": "Pustiť sa do nej",
        "case_A": [
            "enemy_advantage=0",
            "DISTRACT_PREDATOR"
        ],
        "case_B": "Predátorka_2",
        "enemy_escape_delayed": "WRECKS_PREDATOR_2"
    },
    "Predátorka_2": {
        "image": "assets/PLACEHOLDER.png",
        "type": "Predátorka"
    },
    "WRECKS_PREDATOR": {
        "image": "assets/WRECKS_PREDATOR.png",
        "initial_msg": "Skautka, ktorú si nezabil, ušla a zanechala pachovú stopu. Vďaka nej ťa teraz našla predátorka.",
        "choice_A": "Odlákať ju kameňom",
        "choice_B": "Pustiť sa do nej",
        "case_A": [
            "enemy_advantage=0",
            "DISTRACT_PREDATOR"
        ],
        "case_B": "Predátorka_2",
        "enemy_escape_delayed": "WRECKS_PREDATOR_2"
    },
    "WRECKS": {
        "skills": [
            "suck"
        ],
        "difficulty": 6,
        "threat": 5,
        "image": "assets/WRECKS.png",
        "initial_msg": "Vytiahneš hadicu a ideš na to.",
        "success_msg": "Vyšlo to, máš benzín.",
        "threat_msg": "Vdýchneš benzín a začneš kašľať. To môže prilákať Somory.",
        "threat_avoided_msg": "Zacítiš si výpary a prestaneš ťahať v poslednej chvíli. Skoro sa ti benzín dostal do úst.",
        "failure_msg": "Nepodarilo sa ti to. Buď tam nič nie je, alebo to jednoducho nevieš.",
        "case_success": "CAR_3",
        "case_threat": "stress+2",
        "case_failure": "WRECKS_PREDATOR_2",
        "back": true
    },
    "BASEMENT_PREDATOR_2": {
        "image": "assets/BASEMENT.png",
        "initial_msg": "Opäť ťa objavila predátorka.",
        "choice_A": "Odlákať ju kameňom",
        "choice_B": "Pustiť sa do nej",
        "case_A": [
            "enemy_advantage=0",
            "flag_distractBasment:true",
            "DISTRACT_PREDATOR"
        ],
        "case_B": [
            "Predátorka_1",
            "CITY_2"
        ],
        "enemy_escape_delayed": "BASEMENT_PREDATOR_2"
    },
    "Predátorka_1": {
        "image": "assets/PLACEHOLDER.png",
        "type": "Predátorka"
    },
    "BASEMENT_PREDATOR": {
        "image": "assets/BASEMENT.png",
        "initial_msg": "Skautka, ktorú si nezabil, ušla a zanechala pachovú stopu. Vďaka nej ťa teraz našla predátorka.",
        "choice_A": "Odlákať ju kameňom",
        "choice_B": "Pustiť sa do nej",
        "case_A": [
            "enemy_advantage=0",
            "flag_distractBasment:true",
            "DISTRACT_PREDATOR"
        ],
        "case_B": [
            "Predátorka_1",
            "CITY_2"
        ],
        "enemy_escape_delayed": "BASEMENT_PREDATOR"
    },
    "CAR_3": {
        "trigger_delayed": [
            "BASEMENT_PREDATOR",
            "WRECKS_PREDATOR",
            "WRECKS_PREDATOR_2",
            "PURITÁN_2"
        ],
        "image": "assets/CAR.png",
        "initial_msg": "Máš benzín, nie je to veľa, ale môžeš pokračovať v ceste kým nenájdeš viac.",
        "choice_A": "Už tu nemám čo robiť. (dokončiť hru)",
        "case_A": "GAME_OVER"
    },
    "CAR_2": {
        "image": "assets/CAR.png",
        "initial_msg": "Stále potrebuješ benzín, čo chceš robiť?",
        "choice_A": "Idem do mesta.",
        "choice_B": "Budem smutne sedieť a plakať.",
        "case_A": "CITY",
        "case_B": "CAR_2",
        "choice_C": "Idem K vysielaču",
        "case_C": [
            "FOREST_PATH_0",
            "TOWER_1"
        ],
        "choice_D": "Idem k chatrči.",
        "case_D": "SHACK_0",
        "choice_E": "Idem pešo.",
        "case_E": "WALK_0"
    },
    "CITY_2": {
        "trigger_delayed": [
            "BASEMENT_PREDATOR"
        ],
        "image": "assets/CITY.png",
        "initial_msg": "Vydáš sa do centra alebo späť k autu?",
        "choice_A": "Do centra.",
        "choice_B": "Späť k autu.",
        "case_A": "WRECKS_0",
        "case_B": "CAR_1",
        "choice_C": "",
        "case_C": ""
    },
    "IN_BASEMENT": {
        "image": "assets/BASEMENT.png",
        "initial_msg": "Nachádzaš sa v starej garáži. Kedysi sa tu niekto ukrýval, ale už tu dlho nebol. Môžeš to tu skúsiť prehľadať.",
        "skills": [
            "throw"
        ],
        "difficulty": 7,
        "threat": 2,
        "success_msg": "Nájdeš bandasku.",
        "threat_msg": "Niečo ťa pichlo. Všimneš si, že to bola použitá injekčná striekačka. Môžeš len dúfať, nebola nakazená HIV alebo podobným svinstvom.",
        "threat_avoided_msg": "Pri dôkladnom prehrabávaní si všimneš injekčnú striekačku. Nechýbalo veľa a pichla by ťa do ruky.",
        "failure_msg": "Nájdeš aspoň bandasku, ale inak nič. Bude lepšie ísť späť.",
        "case_success": [
            "flag_container:true",
            "item_BANDASKA+1",
            "set_NO_HOSE_NO_CONTAINER_false",
            "set_NO_CONTAINER_false",
            "if_hose:false_set_NO_HOSE_true",
            "if_hose:true_set_WRECKS_true",
            "if_hose:true_set_SUCK_true",
            "CITY_2",
            "set_BASEMENT_ENTRANCE_false"
        ],
        "case_threat": "stress+1",
        "case_failure": [
            "flag_container:true",
            "item_CONTAINER+1",
            "set_NO_HOSE_NO_CONTAINER_false",
            "set_NO_CONTAINER_false",
            "if_hose:false_set_NO_HOSE_true",
            "if_hose:true_set_WRECKS_true",
            "if_hose:true_set_SUCK_true",
            "CITY_2"
        ]
    },
    "Skautka_2": {
        "image": "assets/PLACEHOLDER.png",
        "type": "Skautka"
    },
    "BASEMENT_DISTRACT": {
        "skills": [
            "throw"
        ],
        "difficulty": 7,
        "threat": 2,
        "image": "assets/BASEMENT.png",
        "initial_msg": "Na zemi nájdeš sklenenú fľašu. Hádžeš ju čo najďalej. Snáď to Skautku odláka.",
        "success_msg": "Podarilo sa, uteká za fľašou.",
        "threat_msg": "Fľaša bola rozbitá. Porežeš si ruku.",
        "threat_avoided_msg": "Všimneš si, že fľaša je rozbitá a hodíš ju opatrne. Neporežeš sa.",
        "failure_msg": "Skautka kašle na fľašu a ide po tebe.",
        "case_success": "IN_BASEMENT",
        "case_success_delayed": "BASEMENT_PREDATOR",
        "case_threat": "stress+1",
        "case_failure": [
            "Skautka_2",
            "IN_BASEMENT"
        ],
        "enemy_escape_delayed": "BASEMENT_PREDATOR"
    },
    "BASEMENT_ENCOUNTER": {
        "image": "assets/BASEMENT.png",
        "initial_msg": "Čo urobíš so Skautkou?",
        "choice_A": "Odlákať ju preč.",
        "choice_B": "Poďme sa biť.",
        "case_A": "BASEMENT_DISTRACT",
        "case_B": [
            "Skautka_2",
            "IN_BASEMENT"
        ],
        "enemy_escape_delayed": "BASEMENT_PREDATOR"
    },
    "EXPLORE_BASEMENT": {
        "skills": [
            "PLÝŽENIE"
        ],
        "difficulty": 8,
        "threat": 4,
        "image": "assets/BASEMENT.png",
        "initial_msg": "Blížiš sa ku vchodu. Hluk zrazu nachvíľu prestane.",
        "success_msg": "Všimneš si, že tam je ďalšia Skautka.",
        "threat_msg": "Stúpiš na suchú vetvičku a Skautka to počuje. Teraz je na teba pripravená.",
        "threat_avoided_msg": "Takmer stúpiš na suchú vetvičku. To by ťa prezradilo a Skautka by sa na teba stihla pripraviť.",
        "failure_msg": "Vchádzaš dnu a narazíš na Skautku. Priprav sa na boj.",
        "case_success": "BASEMENT_ENCOUNTER",
        "case_success_delayed": "BASEMENT_PREDATOR",
        "case_threat": "enemy_advantage+1",
        "case_failure": [
            "Skautka_2",
            "IN_BASEMENT"
        ],
        "enemy_escape_delayed": "BASEMENT_PREDATOR"
    },
    "BASEMENT_ENTRANCE": {
        "image": "assets/BASEMENT.png",
        "initial_msg": "Objavíš vstup do pivnice. Zdá sa, že tam niečo šramoce. Ideš dole?",
        "choice_A": "Preskúmať.",
        "choice_B": "Ísť späť.",
        "case_A": "EXPLORE_BASEMENT",
        "case_B": "CITY_2"
    },
    "CITY": {
        "image": "assets/CITY.png",
        "initial_msg": "Prichádzaš do mesta. Vydáš sa do centra alebo na sídlisko?",
        "choice_A": "Do centra.",
        "choice_B": "Na sídlisko.",
        "case_A": "WRECKS_0",
        "case_B": "BASEMENT_ENTRANCE",
        "choice_C": "Späť k autu.",
        "case_C": "CAR_1"
    },
    "Skautka_1": {
        "image": "assets/PLACEHOLDER.png",
        "type": "Skautka"
    },
    "SNEAK": {
        "back": true,
        "skills": [
            "PLÝŽENIE"
        ],
        "difficulty": 8,
        "threat": 3,
        "image": "assets/CITY.png",
        "initial_msg": "Snažíš sa prekĺznuť. Zdá sa, že zatiaľ si ťa nevšimla. (vyber si kartu)",
        "success_msg": "Úspech! Skautka si ťa nevšimla a môžeš ísť ďalej.",
        "threat_msg": "Pozeráš na Skautku, nevšimneš si plot pod nohami a poškriabeš sa na ňom.",
        "threat_avoided_msg": "Takmer sa poškriabeš na plote. Ale keďže si dávaš pozor, nič sa ti nestane.",
        "failure_msg": "Všimla si ťa a rozbehla sa za tebou!",
        "case_success": [
            "set_CITY_true",
            "CITY",
            "set_CITY_0_false"
        ],
        "case_success_delayed": [
            "WRECKS_PREDATOR",
            "BASEMENT_PREDATOR"
        ],
        "case_threat_delayed": "",
        "case_failure_delayed": "",
        "case_threat": "stress+1",
        "case_failure": [
            "Skautka_1",
            "set_CITY_true",
            "CITY",
            "set_CITY_0_false"
        ],
        "enemy_escape_delayed": [
            "WRECKS_PREDATOR",
            "BASEMENT_PREDATOR"
        ]
    },
    "CAR": {
        "skills": [
            "climb"
        ],
        "image": "assets/CAR.png",
        "initial_msg": "Si pri svojom aute. Ktoré má prázdnu nádrž.",
        "choice_A": "Do mesta!",
        "choice_B": "Porozhliadnuť sa.",
        "case_A": "CITY_0",
        "case_B": "LOOK_AROUND",
        "choice_C": "Kašlať na to, idem pešo...",
        "case_C": "WALK_0"
    },
    "TEST": {
        "image": "assets/CAR.png",
        "initial_msg": "Si pri svojom aute. Ktoré má prázdnu nádrž.",
        "choice_A": "test",
        "case_A": [
            "TEST2",
            "stress+1"
        ]
    },
    "TEST2": {
        "image": "assets/CAR.png",
        "initial_msg": "Si pri svojom aute. Ktoré má prázdnu nádrž.",
        "choice_A": "test",
        "case_A": [
            "TEST",
            "stress+1"
        ]
    },
    "START": {
        "image": "assets/CAR.png",
        "initial_msg": "Už mesiac cestuješ po krajine. Bez akéhokoľvek kontaktu. Hľadáš ľudí. Alebo Hybridov. Hocikoho.",
        "next": "CAR",
        "initial_msg_1": "Čo ak už nikto nezostal?",
        "initial_msg_2": "Nie. Tak to nesmie byť. Potom by už nemalo zmysel pokračovať.",
        "initial_msg_3": "A teraz sa ti navyše minul benzín. Možno nejaký nájdeš v neďalekom meste."
    },
    "CITY_0": {
        "initial_msg": "Medzi tebou a mestom sa ale motá skautka. Čo urobíš?",
        "case_success": "",
        "case_failure": "",
        "case_A": [
            "Skautka_1",
            "if_Skautka_1:false_set_CITY_true",
            "CITY"
        ],
        "case_B": "SNEAK",
        "choice_A": "Zaútočiť na skautku.",
        "choice_B": "Pokúsiť sa ju nenápadne obísť.",
        "enemy_escape_delayed": [
            "WRECKS_PREDATOR",
            "BASEMENT_PREDATOR"
        ],
        "back": true,
        "image": "assets/CITY.png"
    },
    "LOOK_AROUND": {
        "image": "assets/PLACEHOLDER.png",
        "initial_msg": "Na kopci v diaľke vidíš vysielač.",
        "case_success": "",
        "case_failure": "",
        "choice_A": "Ísť k vysielaču",
        "case_A": "TOWER_0",
        "choice_C": "",
        "case_C": "",
        "back": true
    },
    "TOWER_0": {
        "image": "assets/PLACEHOLDER.png",
        "initial_msg": "Najkratšia cesta vedie cez priamy svah. Vidíš aj nejakú lesnú cestu, ktorá vedie popri svahu - možno k vysielaču, ale to nevieš.",
        "case_success": "",
        "case_failure": "",
        "choice_A": "Idem krížom po svahu.",
        "case_A": "SLOPE",
        "choice_B": "Skúsim tú cestu.",
        "case_B": "FOREST_PATH",
        "choice_C": "Idem radšej späť.",
        "case_C": "CAR_1",
        "choice_D": "",
        "case_D": ""
    },
    "WALK_0": {
        "image": "assets/PLACEHOLDER.png",
        "initial_msg": "Pred tebou je nekonečne dlhá cesta.",
        "case_success": "",
        "case_failure": "",
        "choice_A": "Toto nikam nevedie, idem späť...",
        "case_A": "CAR",
        "choice_B": "Do večera snáď niekam prídem.",
        "case_B": "WALK_1"
    },
    "FOREST_PATH": {
        "image": "assets/PLACEHOLDER.png",
        "initial_msg": "Zatiaľ to nevyzerá, že cesta vedie hore. Objavíš ale akúsi starú chatrč.",
        "case_success": "",
        "case_failure": "",
        "choice_A": "Idem ďalej.",
        "case_A": "FOREST_PATH_0",
        "choice_B": "Prehľadám chatrč.",
        "case_B": "SHACK_0",
        "back": true
    },
    "SLOPE": {
        "initial_msg": "Svah je strmý a pôda je vlhká, toto nebude jednoduché.",
        "case_success": "CLIFF",
        "case_failure": "TOWER_0",
        "skills": [
            "climb"
        ],
        "difficulty": 9,
        "threat": 3,
        "image": "assets/PLACEHOLDER.png",
        "success_msg": "Je to náročné, ale podarí sa ti vyškriabať sa hore.",
        "threat_msg": "Šmykneš sa, zvezieš sa niekoľko metrov, pri čom sa zoderieš a doudieraš.",
        "threat_avoided_msg": "Šmykne sa ti noha, ale stihneš sa chytiť konára.",
        "failure_msg": "Tento pokus nevyšiel.",
        "case_threat": "stress+1"
    },
    "CAR_1": {
        "image": "assets/CAR.png",
        "initial_msg": "Si pri aute a stále nemáš benzín.",
        "choice_A": "Idem k vysielaču.",
        "case_A": "TOWER_0",
        "choice_B": "Idem do mesta.",
        "case_B": [
            "CITY",
            "CITY_0"
        ],
        "choice_C": "Idem pešo...",
        "case_C": "WALK_0"
    },
    "WALK_1": {
        "image": "assets/PLACEHOLDER.png",
        "initial_msg": "Kráčaš a akoby si bol stále na tom istom mieste. Len keď sa obzieš dozadu, vidíš, že auto sa ti vzďaľuje.",
        "case_success": "",
        "case_failure": "",
        "choice_A": "Kráčam ďalej.",
        "case_A": [
            "SKAUTKA_0",
            "SKAUTKA_4",
            "WALK_2"
        ],
        "choice_B": "Vrátim sa.",
        "case_B": "WALK_0"
    },
    "TOWER_1": {
        "image": "assets/PLACEHOLDER.png",
        "initial_msg": "Si pri vysielači. Je jasne označený červeným krížom - to znamená, že patrí Puritánom.",
        "case_success": "",
        "case_failure": "",
        "next": [
            "set_FOREST_PATH_0_false",
            "GENERATOR"
        ]
    },
    "FOREST_PATH_0": {
        "image": "assets/PLACEHOLDER.png",
        "initial_msg": "Narazíš na nejakého muža, on ťa ešte nezbadal. Týchto poznáš, je to Puritán. Ak zistí, že si Hybrid, nebude sa s tebou maznať.",
        "case_success": "",
        "case_failure": "",
        "choice_A": "Zobrať nohy na ramená.",
        "case_A": "PURITAN_ESCAPE",
        "choice_B": "Skúsim ho osloviť.",
        "case_B": "PURITAN_D_0",
        "choice_C": "Napadnem ho.",
        "case_C": [
            "PURITÁN_1",
            "set_TOWER_1_true",
            "set_FOREST_PATH_0_false",
            "TOWER_1"
        ],
        "choice_D": "Nenápadne ho obídem.",
        "case_D": "FOREST_PATH_SNEAK",
        "choice_E": "",
        "case_E": ""
    },
    "SHACK_0": {
        "image": "assets/PLACEHOLDER.png",
        "initial_msg": "Stojíš pri starej chatrči. Je obrastená tŕnistým krovím. Ak tu niekto za posledný mesiac bol, dal si naozaj záležať na tom, aby to nebolo vidno. Chceš sa skúsiť dostať dnu?",
        "case_success": "",
        "case_failure": "",
        "choice_A": "Skúsim dvere.",
        "case_A": "SHACK_DOOR_BREAK",
        "choice_B": "Skúsim to oknom.",
        "case_B": "SHACK_WINDOW",
        "choice_C": "Prehľadám okolie.",
        "case_C": "SHACK_LOOK_AROUND",
        "back": true,
        "choice_E": "Idem dnu.",
        "case_E": "SHACK_1"
    },
    "FOREST_PATH_SNEAK": {
        "image": "assets/PLACEHOLDER.png",
        "initial_msg": "Obchádzaš cestu cez les ponad Puritána.",
        "case_success": [
            "set_FOREST_PATH_0_false",
            "set_TOWER_1_true",
            "TOWER_1"
        ],
        "case_failure": [
            "BACK_ACTION_1"
        ],
        "trigger_delayed": "difficulty+1",
        "skills": [
            "PLÝŽENIE"
        ],
        "difficulty": 7,
        "threat": 4,
        "success_msg": "Už by ťa nedobehol, môžeš ísť ďalej.",
        "threat_msg": "Všimol si ťa a zazvonil na nejaký zvon, určite privolal ďalších.",
        "threat_avoided_msg": "Takmer si ťa všimne, ale v poslednej chvíli zamrzneš za stromom.",
        "failure_msg": "Dáva si priveľký pozor, nedarí sa ti obísť ho.",
        "case_threat_delayed": "PURITÁN_2"
    },
    "PURITAN_D_0": {
        "initial_msg": "PURITÁN: Čo si zač? Kde si sa tu vzal? Ty nie si od nás. Nie si náhodou Hybrid?",
        "case_success": "",
        "case_failure": "",
        "image": "assets/FOREST.png",
        "choice_A": "Nie, som človek. Stratil som sa. Potrebujem pomoc.",
        "case_A": "PURITAN_LIE",
        "choice_B": "Som pánom tohto lesa, vzdaj sa.",
        "case_B": "PURITAN_THREATEN"
    },
    "PURITÁN_1": {
        "image": "assets/PLACEHOLDER.png",
        "initial_msg": "Nový vytvorený príbehový uzol.",
        "case_success": "",
        "case_failure": "",
        "type": "Puritán"
    },
    "PURITAN_LIE": {
        "initial_msg": "Dúfaš, že ti uverí.",
        "case_success": "PURITAN_CONVINCE",
        "case_failure": "PURITAN_DONT_CONVINCE",
        "skills": [
            "persuade",
            "lie"
        ],
        "difficulty": 8,
        "threat": 4,
        "image": "assets/FOREST.png",
        "success_msg": "PURITÁN: Áno? Pokračuj.",
        "threat_msg": "Je presvedčený, že klameš.",
        "threat_avoided_msg": "Zdá sa, že mal podozrenie, ale zažehnal si ho.",
        "failure_msg": "Neverím ti. Vypadni.",
        "case_threat_delayed": "difficulty+1"
    },
    "PURITAN_THREATEN": {
        "initial_msg": "Skúsiš to po zlom.",
        "case_success": "TOWER_1",
        "case_failure": [
            "PURITÁN_1",
            "set_TOWER_1_true",
            "set_FOREST_PATH_0_false",
            "TOWER_1"
        ],
        "skills": [
            "threaten"
        ],
        "difficulty": 8,
        "threat": 4,
        "image": "assets/FOREST.png",
        "success_msg": "Zľakol sa a zdrhá. Môžeš ísť ďalej.",
        "threat_msg": "Zazvonil na nejaký zvon, určite privolal ďalších.",
        "threat_avoided_msg": "Vytiahol nejaký zvon, ale vyrazil si mu ho z ruky.",
        "failure_msg": "Len si ho naštval, idete sa biť.",
        "case_threat_delayed": "PURITÁN_2"
    },
    "PURITAN_CONVINCE": {
        "image": "assets/PLACEHOLDER.png",
        "initial_msg": "PURITÁN: Tak poď so mnou. U nás nájde útočisko každá zblúdilá duša.\n(vieš, že je to pasca)",
        "case_success": "",
        "case_failure": "",
        "choice_A": "Nechaj ma prejsť.",
        "case_A": "FOREST_PATH_2",
        "choice_B": "Vieš čo, už ťa mám dosť.",
        "case_B": [
            "PURITÁN_1",
            "set_TOWER_1_true",
            "set_FOREST_PATH_0_false",
            "TOWER_1"
        ],
        "choice_C": "Niečo som si zabudol v aute, maj sa.",
        "case_C": "FOREST_PATH_1"
    },
    "PURITAN_DONT_CONVINCE": {
        "image": "assets/PLACEHOLDER.png",
        "initial_msg": "S týmto sa nedohodneš. Ak chceš ísť tadiaľto ďalej, budeš ho musieť poraziť.",
        "case_success": "",
        "case_failure": "",
        "choice_A": "Ideme sa biť.",
        "case_A": [
            "PURITÁN_1",
            "set_FOREST_PATH_0_false",
            "set_TOWER_1_true",
            "TOWER_1"
        ],
        "choice_B": "Vrátim sa.",
        "case_B": "FOREST_PATH_1",
        "choice_C": "",
        "case_C": ""
    },
    "FOREST_PATH_1": {
        "image": "assets/PLACEHOLDER.png",
        "initial_msg": "Si späť pri chatrči.",
        "case_success": "",
        "case_failure": "",
        "choice_B": "Idem skúsiť svah.",
        "case_B": "SLOPE",
        "choice_C": "Idem k autu.",
        "case_C": "CAR_2",
        "choice_D": "Idem dnu.",
        "case_D": [
            "SHACK_1",
            "SHACK_2"
        ],
        "choice_E": "Idem do pivnice.",
        "case_E": "SHACK_CELLAR",
        "choice_A": "Pokračujem po lesnej ceste.",
        "case_A": "FOREST_PATH_0"
    },
    "PURITÁN_2": {
        "image": "assets/PLACEHOLDER.png",
        "initial_msg": "Ten prekliaty zvonec. Bol to alarm a privolal ďalších.",
        "case_success": "",
        "case_failure": "",
        "next": [
            "Puritán",
            "Puritán"
        ]
    },
    "FOREST_PATH_2": {
        "initial_msg": "Vidíš, že Puritán váha.",
        "case_success": [
            "set_FOREST_PATH_0_false",
            "set_TOWER_1_true",
            "TOWER_1"
        ],
        "case_failure": [
            "PURITÁN_1",
            "set_TOWER_1_true",
            "set_FOREST_PATH_0_false",
            "TOWER_1"
        ],
        "trigger_delayed": "difficulty+1",
        "skills": [
            "convince",
            "threaten"
        ],
        "difficulty": 9,
        "threat": 3,
        "image": "assets/FOREST.png",
        "success_msg": "Môžeš ísť ďalej.",
        "threat_msg": "Zazvonil na nejaký zvon, určite privolal ďalších.",
        "threat_avoided_msg": "Vytiahol nejaký zvon, ale vyrazil si mu ho z ruky.\n\nPURITÁN: Ešte sme neskončili...",
        "failure_msg": "Naštval sa, priprav sa na boj.",
        "case_threat_delayed": "PURITÁN_2"
    },
    "CLIFF": {
        "image": "assets/PLACEHOLDER.png",
        "initial_msg": "Ešte ani zďaleka nemáš vyhrané. Aby si sa dostal k vysielaču, potrebuješ zdolať vysoké bralo. Všimneš si aj úzky chodník, ktorý ide po obvode kopca.",
        "case_success": "",
        "case_failure": "",
        "choice_A": "To zvládnem.",
        "case_A": "CLIFF_CLIMB",
        "choice_B": "Idem späť.",
        "case_B": "TOWER_0",
        "choice_C": "Použijem lano.",
        "case_C": "CLIFF_CLIMB_0",
        "choice_D": "Idem po chodníku.",
        "case_D": "TRACK",
        "back": true
    },
    "CLIFF_CLIMB": {
        "initial_msg": "Utrieš si špinavé dlane a vrhneš sa na skaly.",
        "case_success": "TOWER_2",
        "case_failure": "CLIFF",
        "skills": [
            "climb"
        ],
        "difficulty": 10,
        "threat": 4,
        "image": "assets/FOREST.png",
        "success_msg": "Si hore!",
        "threat_msg": "Už po prvých pár metroch sa chytíš koreňa, ktorý sa uvoľní a spadneš.",
        "threat_avoided_msg": "Vyskúšaš trčiaci koreň, ale zistíš, že je suchý, kým sa naň zavesíš. To mohlo dopadnúť zle.",
        "failure_msg": "Už nevládzeš, potrebuješ zliezť dole.",
        "case_threat": "stress+1"
    },
    "GENERATOR": {
        "image": "assets/PLACEHOLDER.png",
        "initial_msg": "Vysielač je napojený na generátor. Tam určite bude benzín.",
        "case_success": "",
        "case_failure": "",
        "choice_A": "Vysať benzín. Puritáni si ho nezaslúžia.",
        "case_A": "SUCK",
        "choice_B": "K hybridom sa správajú ako monštrá, ale sú to ľudia. Nebudem od nich kradnúť.",
        "case_B": "CAR_5",
        "choice_C": "Vysať benzín.",
        "case_C": "NO_HOSE",
        "choice_D": "Vysať benzín.",
        "case_D": "NO_HOSE_NO_CONTAINER",
        "choice_E": "Vysať benzín.",
        "case_E": "NO_CONTAINER"
    },
    "SUCK": {
        "initial_msg": "Klasika - hadica a bandaska.",
        "case_success": "CAR_3",
        "case_failure": "GENERATOR",
        "difficulty": 6,
        "threat": 4,
        "image": "assets/TOWER.png",
        "success_msg": "Podarilo sa, máš benzín!",
        "threat_avoided_msg": "Zacítiš si výpary a prestaneš ťahať v poslednej chvíli. Skoro sa ti benzín dostal do úst.",
        "threat_msg": "Vdýchneš benzín a zakašleš sa.",
        "failure_msg": "Nedarí sa ti. Puritáni to musia mať nejak zabezpečené proti tejto primitívnej metóde.",
        "case_threat": "stress+1",
        "back": true
    },
    "CAR_5": {
        "image": "assets/CAR.png",
        "initial_msg": "Si pri aute.",
        "case_success": "",
        "case_failure": "",
        "choice_A": "Idem do mesta.",
        "case_A": "CITY_0",
        "choice_B": "Idem pešo...",
        "case_B": "WALK_0",
        "choice_C": "Idem k chatrči.",
        "case_C": "SHACK_0",
        "choice_D": "Idem k vysielaču.",
        "case_D": [
            "FOREST_PATH_0",
            "TOWER_1"
        ]
    },
    "SHACK_LOOK_AROUND": {
        "initial_msg": "Kvôli porastu je ťažké pohybovať sa v blízkosti chaty.",
        "case_success": [
            "set_SHACK_WINDOW_false",
            "set_SHACK_DOOR_false",
            "set_SHACK_LOOK_AROUND_false",
            "set_SHACK_CELLAR_true",
            "SHACK_CELLAR"
        ],
        "case_failure": "SHACK_0",
        "back": true,
        "skills": [
            "ŠPEHOVANIE",
            "ZMYSLY"
        ],
        "difficulty": 8,
        "threat": 4,
        "image": "assets/SHACK.png",
        "success_msg": "Objavíš tajný vchod, vedie do pivnice a vôbec nie je zamknutý.",
        "threat_msg": "Poriadne sa na kríkoch doškriabeš.",
        "threat_avoided_msg": "Máš čo robiť, aby ti tŕne nerozdriapali kožu. Ale nejakým zázrakom sa ti to podarí.",
        "failure_msg": "Nepodarí sa ti k chatrči veľmi priblížiť. Asi tam aj tak nič nie je.",
        "case_threat": "stress+1"
    },
    "SHACK_DOOR_BREAK": {
        "initial_msg": "Dvere sú zaistené kovovou tyčou a zámkom. Môžeš ich skúsiť vykopnúť.",
        "skills": [
            "SILA"
        ],
        "difficulty": 9,
        "threat": 2,
        "image": "assets/SHACK.png",
        "success_msg": "Dvere neodolali tvojmu šarmu.",
        "threat_msg": "Pri vykopávaní dverí si poriadne narazíš nohu. To ešte chvíľu budeš cítiť.",
        "threat_avoided_msg": "Ak by dvere vykopával niekto iný, asi by si ublížil. Ale nie ty. Ty máš techniku. Však to nerobíš prvý raz?",
        "failure_msg": "S týmito dverami len tak nepohneš.",
        "case_success": [
            "set_SHACK_0_false",
            "flag_shackOpen:true",
            "set_SHACK_WINDOW_false",
            "set_SHACK_DOOR_BREAK_false",
            "flag_doorOpen:true",
            "set_SHACK_1_true",
            "set_UNLOCK_CELLAR_false",
            "SHACK_1"
        ],
        "case_threat": "stress+1",
        "case_failure": "if_fromCellar:true_SHACK_CELLAR_else_SHACK_0",
        "back": true
    },
    "SHACK_WINDOW": {
        "initial_msg": "Na oknách sú mreže. Ale sú staré a hrdzavé. Skús ich vytrhnúť.",
        "case_success": [
            "set_SHACK_0_false",
            "flag_shackOpen:true",
            "set_SHACK_WINDOW_false",
            "set_SHACK_DOOR_false",
            "set_SHACK_LOOK_AROUND_false",
            "set_SHACK_1_true",
            "SHACK_1"
        ],
        "case_failure": "SHACK_0",
        "skills": [
            "SILA"
        ],
        "difficulty": 8,
        "threat": 3,
        "image": "assets/SHACK.png",
        "success_msg": "Zaprieš sa do mreží, zapraská drevo a prekotíš sa dozadu aj s mrežami. Okno už taký problém nerobilo. Môžeš ísť dnu.",
        "threat_msg": "Všade to prekliate tŕnie. Už máš doškriabané ruky.",
        "threat_avoided_msg": "Stále si musíš dávať pozor na tŕnie. Ale aspoň si nedoškriabeš ruky. Tentoraz.",
        "failure_msg": "Mreže sú pevnejšie, ako sa zdalo.",
        "case_threat": "stress+1",
        "back": true
    },
    "SHACK_CELLAR": {
        "image": "assets/PLACEHOLDER.png",
        "initial_msg": "Ocitneš sa v pivnici.",
        "case_success": "",
        "case_failure": "",
        "choice_A": "Ísť hore.",
        "case_A": [
            "SHACK_2",
            "SHACK_1",
            "SHACK_DOOR_BREAK"
        ],
        "choice_B": "Ísť von.",
        "case_B": "if_shackOpen:true_FOREST_PATH_else_SHACK_0",
        "choice_C": "Prehľadať to tu.",
        "case_C": "SHACK_CELLAR_0"
    },
    "SHACK_1": {
        "image": "assets/PLACEHOLDER.png",
        "initial_msg": "Vojdeš dnu a zacítiš mŕtvolný zápach. Je prítmie, ale vidíš, že chatrč má len jednu veľkú miestnosť - v jednom rohu primitívna kuchynka, v druhom krb a v strede stôl. Okrem toho vidíš dvere do pivnice a rebrík do podkrovia.",
        "case_success": "",
        "case_failure": "",
        "choice_A": "Ísť von.",
        "case_A": "FOREST_PATH_1",
        "choice_B": "Idem do pivnice.",
        "case_B": "if_doorOpen==true_SHACK_CELLAR_else_UNLOCK_CELLAR",
        "choice_C": "Vyleziem po rebríku.",
        "case_C": "SHACK_ATTIC",
        "choice_E": "Prehľadať to tu.",
        "case_E": [
            "SHACK_EXPLORE"
        ]
    },
    "SHACK_CELLAR_0": {
        "initial_msg": [
            "V pivnici je naozaj bordel. Nástroje, ktoré už ani nevieš, načo slúžia - vedrá, debny..."
        ],
        "case_success": [
            "flag_hose:true",
            "item_HADICA+1",
            "set_NO_HOSE_NO_CONTAINER_false",
            "set_NO_HOSE_false",
            "if_container:false_set_NO_CONTAINER_true",
            "if_container:true_set_WRECKS_true",
            "if_container:true_set_SUCK_true",
            "weapon+sekera",
            "set_SHACK_CELLAR_0_false",
            "SHACK_CELLAR"
        ],
        "case_failure": [
            "flag_hose:true",
            "item_HADICA+1",
            "set_NO_HOSE_NO_CONTAINER_false",
            "set_NO_HOSE_false",
            "if_container:false_set_NO_CONTAINER_true",
            "if_container:true_set_WRECKS_true",
            "if_container:true_set_SUCK_true",
            "SHACK_CELLAR"
        ],
        "skills": [
            "ZMYSLY",
            "ŠPEHOVANIE"
        ],
        "difficulty": 7,
        "threat": 2,
        "image": "assets/SHACK.png",
        "success_msg": [
            "Zdalo sa, že žiadna z tých harabúrd nebude užitočná, ale aha - objavíš sekeru v celkom fajn stave! A okrem nej záhradnú hadicu."
        ],
        "threat_msg": "Pri prehľadávaní políc ti niečo spadne na hlavu. Nevieš, na čo to slúži, ale vieš, že keď to človeka trafí do hlavy, bolí to.",
        "threat_avoided_msg": "Pri prehľadávaní políc niečo zhodíš a takmer ti to spadne na hlavu. V poslednej chvíli sa uhneš.",
        "failure_msg": "Nájdeš záhradnú hadicu, ale inak nič, čo by sa dalo využiť.",
        "case_threat": "stress+1",
        "back": true
    },
    "UNLOCK_CELLAR": {
        "image": "assets/PLACEHOLDER.png",
        "initial_msg": "Dvere sú odomknuté.",
        "case_success": "",
        "case_failure": "",
        "next": [
            "flag_doorOpen:true",
            "set_SHACK_DOOR_0_false",
            "set_SHACK_CELLAR_true",
            "set_UNLOCK_CELLAR_false",
            "SHACK_1",
            "SHACK_2"
        ]
    },
    "SHACK_ATTIC": {
        "initial_msg": "Zápach je neznesiteľný - evidentne sa blížiš k jeho zdroju. Ak to vydržíš, môžeš to tu skúsiť prehľadať.",
        "case_success": [
            "set_SHACK_0_false",
            "set_SHACK_1_false",
            "set_SHACK_2_true",
            "item_LANO+1",
            "SHACK_2"
        ],
        "case_failure": "SHACK_1",
        "back": true,
        "skills": [
            "ZMYSLY",
            "ŠPEHOVANIE"
        ],
        "difficulty": 9,
        "threat": 3,
        "image": "assets/SHACK.png",
        "threat_msg": "Nevydržíš to a vyvrátiš obed. Nie, že by bolo jedla nazvyš.",
        "success_msg": "Objavíš mŕtvolu, ako sa hovorí - v pokročilom štádiu rozkladu - a pri nej nejaké papiere. Papiere rýchlo zoberieš. Nájdeš aj staré lano, ale potom musíš ísť dole.",
        "threat_avoided_msg": "Napne ťa, ale z posledných síl zvratky zatlačíš späť.",
        "failure_msg": "Tu už nevydržíš ani sekundu. Musíš ísť späť.",
        "case_threat": "stress+1",
        "trigger_delayed": "item"
    },
    "SHACK_2": {
        "image": "assets/PLACEHOLDER.png",
        "initial_msg": "Si späť v hlavnej miestnosti chatrče. Na stole sú papiere, ktoré boli pri mŕtvole.",
        "case_success": "",
        "case_failure": "",
        "choice_A": "Ísť von.",
        "case_A": "FOREST_PATH_1",
        "case_D": "if_doorOpen==true_SHACK_CELLAR_else_UNLOCK_CELLAR",
        "back": false,
        "choice_B": [
            "Prečítam si",
            "čo je na tých papieroch."
        ],
        "case_B": "DEAD_LETTERS",
        "choice_D": "Idem do pivnice.",
        "choice_E": "Prehľadať to tu.",
        "case_E": "SHACK_EXPLORE"
    },
    "SHACK_EXPLORE": {
        "initial_msg": "Je tu málo svetla, ale niečo možno nájdeš.",
        "case_success": [
            "nôž+3",
            "brokovnica+5",
            "weapon+brokovnica",
            "weapon+nôž",
            "set_SHACK_EXPLORE_false",
            "if_bottleBroken:true_SHACK_1_else_SHACK_EXPLORE_2"
        ],
        "case_threat": "flag_bottleBroken:true",
        "case_failure": [
            "set_SHACK_EXPLORE_false",
            "if_bottleBroken:true_SHACK_1_else_SHACK_EXPLORE_2"
        ],
        "back": true,
        "skills": [
            "ŠPEHOVANIE",
            "ZMYSLY"
        ],
        "difficulty": 7,
        "threat": 2,
        "image": "assets/SHACK.png",
        "success_msg": "To vôbec nie je zlé. 3 nože, brokovnica aj s pár nábojmi a na skrini si všimneš fľašu - zdá sa, že slivovica.",
        "threat_msg": "Načiahneš sa po fľašu, do drgneš do skrine, fľaša spadne na zem a rozbije sa. Hej, bola to slivovica. Škoda.",
        "threat_avoided_msg": "Načiahneš sa po fľašu, do drgneš do skrine, fľaša spadne, ale v poslednej sekunde ju chytíš. Otvoríš ju - hej, je to slivovica.",
        "failure_msg": "Nedarí sa ti nájsť nič užitočné. Všimneš si len fľašu na skrini."
    },
    "SHACK_EXPLORE_2": {
        "image": "assets/PLACEHOLDER.png",
        "initial_msg": "Dostaneš sa k slivovici. Tej by bolo škoda.",
        "case_success": "",
        "case_failure": "",
        "next": [
            "item_SLIVOVICA+1",
            "SHACK_1"
        ]
    },
    "DEAD_LETTERS": {
        "image": "assets/PLACEHOLDER.png",
        "initial_msg": "Volám sa Svetlana. Ak si náhodou puritán, tak dúfam, že zhoríš v pekle. To vy ste skutoční diabli, nie my. Ak nie si... Nech si, kto chceš, mne už asi nepomôžeš.",
        "case_success": "",
        "case_failure": "",
        "next": "DEAD_LETTERS_0",
        "choice_A": "Ďalej...",
        "case_A": "DEAD_LETTERS_0",
        "choice_B": "Už ma to nebaví.",
        "case_B": "SHACK_2",
        "back": true
    },
    "DEAD_LETTERS_0": {
        "image": "assets/PLACEHOLDER.png",
        "initial_msg": "Som tu v podstate odkedy dostali Reného, môjho priateľa. Nikdy sme nikomu neublížili. Puritáni to odmietajú pochopiť, ale aj my máme zmysel pre morálku. Aspoň niektorí z nás. My s Reném sme nikdy sme nikomu neublížili.",
        "case_success": "",
        "case_failure": "",
        "case_A": "DEAD_LETTERS_1",
        "choice_A": "Ďalej...",
        "choice_B": "Už ma to nebaví.",
        "case_B": "SHACK_2",
        "back": true
    },
    "DEAD_LETTERS_1": {
        "image": "assets/PLACEHOLDER.png",
        "initial_msg": "Mali sme striktnú zásadu - jedli sme len mäso tých, ktorých sme nemali šancu zachrániť. Nikdy by sme nikoho nenechali zomrieť, aby sme.... Nie to ešte niekoho zabiť! To sú klamstvá!",
        "case_success": "",
        "case_failure": "",
        "case_A": "DEAD_LETTERS_2",
        "choice_A": "Ďalej...",
        "choice_B": "Už ma to nebaví.",
        "case_B": "SHACK_2",
        "back": true
    },
    "DEAD_LETTERS_2": {
        "image": "assets/PLACEHOLDER.png",
        "initial_msg": "Ak nie si jeden z nás, možno sa pýtaš, prečo by vôbec niekto jedol ľudksé mäso. Ale nech sa ľudia pozrú okolo seba! Toto je jediná šanca, ako prežiť. Streliva je stále menej a palicami Somory neutlčieme.",
        "case_success": "",
        "case_failure": "",
        "case_A": "DEAD_LETTERS_6",
        "choice_A": "Ďalej...",
        "choice_B": "Už ma to nebaví.",
        "case_B": "SHACK_2",
        "back": true
    },
    "DEAD_LETTERS_3": {
        "image": "assets/PLACEHOLDER.png",
        "initial_msg": "Ak ľudí požerú Somory, to je akože lepšie? Ale už je to aj tak jedno. Dúfala som, že to vzdajú, no sliedia za mnou ako psy. Míňa sa mi jedlo, ale... Videla som, čo spravili Renému, bastardi! Radšej zomriem od hladu, ako by som sa nimi mala nechať chytiť.",
        "case_success": "",
        "case_failure": "",
        "case_A": "DEAD_LETTERS_4",
        "choice_A": "Ďalej...",
        "choice_B": "Už ma to nebaví.",
        "case_B": "SHACK_2",
        "back": true
    },
    "DEAD_LETTERS_4": {
        "image": "assets/PLACEHOLDER.png",
        "initial_msg": "Už sem raz vtrhli. Bolo to o chlp, našťastie som ich zbadala, kým boli ešte ďaleko. Vyliezla som cez pivnicu a odplazila som sa preč. Odvtedy už tejto skrýši nevenujú veľkú pozornosť. No vždy, keď sa odtiaľto pohnem, narazím na jedného z nich. Už mi je to vlastne aj jedno.",
        "case_success": "",
        "case_failure": "",
        "case_A": "DEAD_LETTERS_5",
        "choice_A": "Ďalej...",
        "choice_B": "Už ma to nebaví.",
        "case_B": "SHACK_2",
        "back": true
    },
    "DEAD_LETTERS_5": {
        "image": "assets/PLACEHOLDER.png",
        "initial_msg": "Po tej mäsiarčine, ktorej sa dopustili na poslednom človeku - pardón - Hybridovi, čo mi zostával, už s týmto svetom nechcem nič mať. Ak ich boh existuje a nezabráni v tom svojim vlastným stúpencom, tak v skutočnosti uctievajú démona a nie boha.",
        "case_success": "",
        "case_failure": "",
        "choice_B": "To je všetko.",
        "case_B": "SHACK_2",
        "back": true
    },
    "DEAD_LETTERS_6": {
        "image": "assets/PLACEHOLDER.png",
        "initial_msg": "Ja už som sa dokonca naučila pohybovať medzi nimi a vôbec na mňa neútočili - ak som nebola v ich teritóriu. To som si kedysi nedokázala ani predstaviť - žiť bez strachu, že ma čoskoro dostane jedna z tých beštií. Ak máme možnosť získať tieto schopnosti, prečo by sme ich nevyužili?",
        "case_success": "",
        "case_failure": "",
        "case_A": "DEAD_LETTERS_3",
        "choice_A": "Ďalej...",
        "choice_B": "Už ma to nebaví.",
        "case_B": "SHACK_2",
        "back": true
    },
    "WRECKS_0": {
        "image": "assets/WRECKS.png",
        "initial_msg": "Objavíš niekoľko vrakov áut. Možno v niektorom budú zvyšky benzínu. Ak máš hadicu a bandasku, môžeš sa k nemu skúsiť dostať.",
        "back": true,
        "choice_A": "Pohľadať benzín.",
        "case_A": "WRECKS",
        "choice_B": "Pohľadať benzín.",
        "case_B": "NO_CONTAINER",
        "case_C": "NO_HOSE_NO_CONTAINER",
        "choice_C": "Pohľadať benzín.",
        "choice_D": "Pohľadať benzín.",
        "case_D": "NO_HOSE"
    },
    "NO_CONTAINER": {
        "image": "assets/PLACEHOLDER.png",
        "initial_msg": "Nemáš bandasku.",
        "case_success": "",
        "case_failure": "",
        "back": true
    },
    "NO_HOSE": {
        "image": "assets/PLACEHOLDER.png",
        "initial_msg": "Nemáš hadicu.",
        "case_success": "",
        "case_failure": "",
        "back": true
    },
    "NO_HOSE_NO_CONTAINER": {
        "image": "assets/PLACEHOLDER.png",
        "initial_msg": "Nemáš bandasku ani hadicu.",
        "case_success": "",
        "case_failure": "",
        "back": true
    },
    "WALK_3": {
        "image": "assets/PLACEHOLDER.png",
        "initial_msg": "Chceš pokračovať?",
        "case_success": "",
        "case_failure": "",
        "choice_A": "Áno.",
        "case_A": [
            "PREDÁTORKA_2",
            "SKAUTKA_3",
            "WALK_4"
        ],
        "choice_B": "Už nie...",
        "case_B": "WALK_0"
    },
    "WALK_4": {
        "image": "assets/PLACEHOLDER.png",
        "initial_msg": "Ešte nemáš dosť?",
        "case_success": "",
        "case_failure": "",
        "choice_A": "Už nevládzem.",
        "case_A": "WALK_0",
        "choice_B": "Nemám! Pome!",
        "case_B": [
            "PREDÁTORKA_3",
            "PREDÁTORKA_4",
            "PREDÁTORKA_5",
            "WALK_5"
        ]
    },
    "SKAUTKA_3": {
        "image": "assets/PLACEHOLDER.png",
        "initial_msg": "Ešte vládzeš?",
        "case_success": "",
        "case_failure": "",
        "type": "Skautka"
    },
    "PREDÁTORKA_2": {
        "image": "assets/PLACEHOLDER.png",
        "initial_msg": "Asi si vošiel do ich teritória!",
        "case_success": "",
        "case_failure": "",
        "type": "Predátorka"
    },
    "SKAUTKA_0": {
        "image": "assets/PLACEHOLDER.png",
        "initial_msg": "Napadne ťa Skautka.",
        "case_success": "",
        "case_failure": "",
        "type": "Skautka"
    },
    "WALK_2": {
        "image": "assets/PLACEHOLDER.png",
        "initial_msg": "Chceš ísť ďalej?",
        "case_success": "",
        "case_failure": "",
        "choice_A": "Áno.",
        "case_A": [
            "PREDÁTORKA_0",
            "WALK_3"
        ],
        "choice_B": "Idem späť.",
        "case_B": "WALK_0"
    },
    "PREDÁTORKA_0": {
        "image": "assets/PLACEHOLDER.png",
        "initial_msg": "Ďalšie Somora!",
        "case_success": "",
        "case_failure": "",
        "type": "Predátorka"
    },
    "WALK_5": {
        "image": "assets/PLACEHOLDER.png",
        "initial_msg": "Ešte nemáš dosť?",
        "case_success": "",
        "case_failure": "",
        "choice_A": "Už nevládzem.",
        "case_A": "WALK_0",
        "choice_B": "Nemám! Pome!",
        "case_B": "GAME_FINISHED"
    },
    "PREDÁTORKA_3": {
        "image": "assets/PLACEHOLDER.png",
        "initial_msg": "Nový vytvorený príbehový uzol.",
        "case_success": "",
        "case_failure": "",
        "type": "Predátorka"
    },
    "PREDÁTORKA_4": {
        "image": "assets/PLACEHOLDER.png",
        "initial_msg": "Nový vytvorený príbehový uzol.",
        "case_success": "",
        "case_failure": "",
        "type": "Predátorka"
    },
    "PREDÁTORKA_5": {
        "image": "assets/PLACEHOLDER.png",
        "initial_msg": "Nový vytvorený príbehový uzol.",
        "case_success": "",
        "case_failure": "",
        "type": "Predátorka"
    },
    "GAME_FINISHED": {
        "image": "assets/PLACEHOLDER.png",
        "initial_msg": "To ty si pravé monštrum! Monštrum, ktoré sa prebilo cez teritórium Somôr a objavilo pevnosť. Koniec hry.",
        "case_success": "",
        "case_failure": ""
    },
    "CLIFF_CLIMB_0": {
        "initial_msg": "Vďaka lanu to bude podstatne jednoduchšie - a bezpečnejšie. Najskôr ho však potrebuješ vyhodiť hore a omotať o nejaký strom na brale.",
        "case_success": "TOWER_2",
        "case_failure": [
            "CLIFF",
            "stress+1"
        ],
        "skills": [
            "climb"
        ],
        "difficulty": 8,
        "threat": 3,
        "image": "assets/FOREST.png",
        "success_msg": "Si hore!",
        "threat_msg": "Šmykne sa ti noha, skĺzneš kúsok dole a spáliš si na lane ruky.",
        "threat_avoided_msg": "Šmykne sa ti noha, ale pevne sa držíš lana. Inak to mohlo byť nepríjemné.",
        "failure_msg": "Lano sa uvoľní a ty padáš dole. Možno to nebol až taký dobý nápad.",
        "case_threat": "stress+1",
        "back": true
    },
    "TOWER_2": {
        "image": "assets/PLACEHOLDER.png",
        "initial_msg": "Si pri vysielači. Je jasne označený červeným krížom - to znamená, že patrí Puritánom.",
        "case_success": "",
        "case_failure": "",
        "next": "GENERATOR"
    },
    "PURITAN_ESCAPE": {
        "initial_msg": "Najskôr ideš opatrne, potom pridáš do kroku.",
        "case_success": "BACK_ACTION_2",
        "case_failure": [
            "PURITÁN_1",
            "set_PURITAN_CONVINCE_false",
            "set_PURITAN_LIE_false"
        ],
        "image": "assets/PLACEHOLDER.png",
        "skills": [
            "PLÝŽENIE",
            "OBRATNOSŤ",
            "ŠPRINT"
        ],
        "difficulty": 7,
        "threat": 3,
        "success_msg": "Podarilo sa ti ujsť.",
        "threat_msg": "Všimol si ťa a spustil poplach.",
        "case_threat_delayed": "PURITÁN_2",
        "threat_avoided_msg": "Ešteže si dávaš pozor, takmer si ťa všimol.",
        "failure_msg": "Dobehne ťa a už je neskoro vysvetľovať, pokladá ťa za nepriateľa."
    },
    "TRACK": {
        "initial_msg": "Možno je to len chodník vyšľapaný zverou a ty len zablúdiš. Navyše sa začína zvažovať, určite nevedie hore k vysielaču.",
        "case_success": "",
        "case_failure": "",
        "back": true,
        "next": "LAKE"
    },
    "LAKE": {
        "initial_msg": "Prichádzaš k jazeru a hneď si všimneš, že na brehu oproti z neho vyčnieva betónový bunker. Časť bunkra - nevieš, aká veľká - sa nachádza pod vodou.",
        "case_success": "",
        "case_failure": "",
        "back": true,
        "choice_A": "Idem k bunkru.",
        "case_A": "BUNKER"
    },
    "BUNKER": {
        "initial_msg": "Okno na bunkri je zamrežované, ale dvere sú otvorené. Má to však jeden háčik - bunker je zatopený a budeš mať vodu tak po prsia.",
        "case_success": "",
        "case_failure": "",
        "choice_A": [
            "To nevadí",
            "prebrodím sa dnu."
        ],
        "case_A": "BUNKER_0",
        "back": true
    },
    "BUNKER_0": {
        "initial_msg": "Dnu preniká trochu svetla, ale aj tak toho veľa nevidíš. Len vrchnú časť stien a strop. Ak je tu niečo zaujímavé, je to pod vodou.",
        "image": "assets/BUNKER.png",
        "choice_A": "Ideme sa potápať!",
        "case_A": "DIVE",
        "choice_B": "Späť pod vodu!",
        "case_B": "DIVE_0",
        "choice_C": "Ešte tam určite niečo bude.",
        "case_C": "DIVE_4"
    },
    "DIVE": {
        "initial_msg": "Nadýchneš sa a zmizneš pod hladinou.",
        "case_success": [
            "item_DEZINFEKCIA+1",
            "set_DIVE_false",
            "set_DIVE_0_true",
            "BUNKER_0"
        ],
        "case_failure": "BUNKER_0",
        "image": "assets/BUNKER.png",
        "difficulty": 9,
        "threat": 4,
        "success_msg": "Vylovíš fľaštičku dezinfekcie. Zdá sa, že voda do nej vôbec neprenikla.",
        "threat_msg": "Do niečoho sa zamotáš. Bojuješ o život. Zdá sa, že tvoje chvíle sú zrátané. Keď už ti dochádzajú poslendé molekuly kyslíka, vyslobodíš sa. Ten pocit už nechceš nikdy zažiť.",
        "case_threat": "stress+2",
        "threat_avoided_msg": "Ako pred sebou habkáš, zacítiš kus dlhej látky, ktorý sa okolo teba začne omotávať. Pre istotu sa vynoríš.",
        "failure_msg": "Vylovíš... kus dreva. To naozaj nestálo za tú námahu."
    },
    "DIVE_0": {
        "initial_msg": "Nádych...",
        "case_success": "BUNKER_1",
        "case_failure": "",
        "image": "assets/BUNKER.png",
        "success_msg": "Objavíš vchod do vedľajšej časti a vynoríš sa tam. Našťasie je tam trochu vzduchu."
    },
    "DIVE_4": {
        "initial_msg": "Bunker nebol až taký opustený, ako sa zdalo. Podarí sa ti vyloviť jeho predchádzajúceho majiteľa.",
        "case_success": "",
        "case_failure": "",
        "next": "BUNKER_0"
    },
    "BUNKER_1": {
        "initial_msg": "Nový vytvorený príbehový uzol.",
        "case_success": "",
        "case_failure": ""
    },
    "TUTORIAL": {
        "initial_msg": "Vitaj v hre Hybrid!",
        "case_success": "",
        "case_failure": "",
        "choice_B": "Preskočiť tutoriál.",
        "case_B": "START",
        "choice_A": "Pokračovať.",
        "case_A": "TUTORIAL_0"
    },
    "TUTORIAL_0": {
        "initial_msg": "Táto digitálna verzia slúži ako doplnok k stolnej hre Hybrid - preto všetky tie kocky a karty.",
        "case_success": "",
        "case_failure": "",
        "choice_A": "Pokračovať.",
        "case_A": "TUTORIAL_1",
        "choice_B": "Preskočiť tutoriál.",
        "case_B": "START"
    },
    "TUTORIAL_1": {
        "initial_msg": "V tomto tutoriále sa dozvieš všetko podstatné. Ak si ho budeš chcieť zopakovať, nájdeš ho v MENU.",
        "case_success": "",
        "case_failure": "",
        "choice_A": "Pokračovať.",
        "case_A": "TUTORIAL_2",
        "choice_B": "Preskočiť tutoriál.",
        "case_B": "START",
        "initial_msg_1": "Toto okno je scrollovateľné, takže ak ti ujde nejaká správa alebo si ju budeš chcieť pripomenúť, všetko nájdeš vyššie."
    },
    "TUTORIAL_2": {
        "initial_msg": "Začneme tým, čo všetko tvorí tvoju postavu. Podstatné je sledovať ukazovateľ stresu. Ten vyjadruje stav tvojej postavy.",
        "case_success": "",
        "case_failure": "",
        "choice_A": "Pokračovať.",
        "case_A": "TUTORIAL_3",
        "choice_B": "Preskočiť tutoriál.",
        "case_B": "START",
        "initial_msg_1": "Pod ním sa nachádza ukazovateľ adrenalínu. Ten poskytne jednorazový bonus, ale okamžite ti zvýši stres na hodnotu nad ním. Môžeš ho použiť, ak veľmi potrebuješ uspieť pri niektorej skúške. Pokojne si to teraz vyskúšaj.",
        "initial_msg_2": ""
    },
    "TUTORIAL_3": {
        "initial_msg": "Hlavnú mechaniku hry ale tvorí systém kariet: OPATRNE, RÁZNE, SMELO a BEZHLAVO.",
        "case_success": "",
        "case_failure": "",
        "choice_A": "Pokračovať.",
        "case_A": "TUTORIAL_4",
        "choice_B": "Preskočiť tutoriál.",
        "case_B": "START",
        "initial_msg_1": "Voľbou karty si vyberáš spôsob, ako budeš konať a každá má svoje výhody aj nevýhody."
    },
    "TUTORIAL_4": {
        "initial_msg": "V pravom hornom rohu je MOTIVÁCIA. Tá určuje kocky, ktorými hodíš pri výbere danej karty. Čím vyššia celková hodnota kociek, tým máš väčšiu šancu na úspech.",
        "case_success": "",
        "case_failure": "",
        "choice_A": "Pokračovať.",
        "case_A": "TUTORIAL_5",
        "choice_B": "Preskočiť tutoriál.",
        "case_B": "START",
        "initial_msg_1": "Motivácia sa porovnáva s NÁROČNOSŤOU. To je jednoducho číslo, ktoré potrebuješ hodiť. Náročnosť býva v rozmedzí 6 až 12. Ak na kockách padne menej, zlyháš."
    },
    "TUTORIAL_5": {
        "initial_msg": "Môžeš si to vyskúšať pri tejto \"výzve\". Náročnosť je veľmi nízka.",
        "case_success": "TUTORIAL_6",
        "case_failure": "TUTORIAL_5",
        "difficulty": 5,
        "threat": 0,
        "success_msg": "Super, podarilo sa.",
        "failure_msg": "Skús to ešte raz."
    },
    "TUTORIAL_6": {
        "initial_msg": "Okrem zlyhania však môžu nastať aj komplikácie. To, či nastanú, určuje HROZBA. Tá máva hodnotu 2 až 6.",
        "case_success": "",
        "case_failure": "",
        "choice_A": "Pokračovať.",
        "case_A": "TUTORIAL_7",
        "choice_B": "Preskočiť tutoriál.",
        "case_B": "START",
        "initial_msg_1": "Ak je tvoj hod nižší ako NÁROČNOSŤ, čelíš HROZBE. To znamená, že sa hodí kockami hrozby (toľko kociek, koľko je hodnota hrozby) a ak sa hrozba naplní, čelíš následkom.",
        "initial_msg_2": "Kockami hrozby sa hádže, aj keď je tvoj hod rovný  náročnosti (vtedy aj uspeješ, aj čelíš hrozbe).",
        "initial_msg_3": "Pred hrozbou ťa ale chráni OPATRNOSŤ ľavom rohu karty. Hrozba sa naplní len v prípade, že na kockách hrozby padne VIAC, ako je tvoja OPATRNOSŤ. Vyskúšaj si to."
    },
    "TUTORIAL_7": {
        "initial_msg": "Vyber si kartu a všimni si, akú má OPATRNOSŤ. Náročnosť je zámerne vysoká, takže zlyháš a potom sa hodí kockami hrozby. Nemusíš sa báť, v hre na takúto náročnosť nenarazíš.",
        "case_success": "",
        "case_failure": "TUTORIAL_8",
        "difficulty": 30,
        "threat": 3,
        "threat_avoided_msg": "Opatrnosť ti pomohla vyhnúť sa HROZBE. V tomto prípade sa hrozbe vyhneš a nič zlé sa ti nestane.",
        "failure_msg": "Teraz sa vyhodnotí HROZBA.",
        "threat_msg": "Hrozba sa naplnila a teraz by sa ti v hre stalo niečo nepríjemné."
    },
    "TUTORIAL_8": {
        "initial_msg": "V hre môžeš čeliť nepriateľom. Vtedy nastane SPOR.",
        "case_success": "",
        "case_failure": "",
        "choice_A": "Pokračovať.",
        "case_A": [
            "SCOUT_DUMMY",
            "TUTORIAL_9"
        ],
        "choice_B": "Preskočiť tutoriál.",
        "case_B": "START",
        "initial_msg_1": "Pri spore môžeš použiť aj dolnú stranu kariet. Môžeš si ich otočiť tlačidlom ↺. Otočenie je čisto vizuálne, nemá vplyv na hru.",
        "initial_msg_2": "Na tejto strane kariet je namiesto opatrnosti INTENZITA. Ide o hodnotu, ktorá zvýši súperovi stres, ak ho trafíš. A to, či ho trafíš, určuje vzájomný hod kockami MOTIVÁCIE. Kto hodí viac, ten trafil.",
        "initial_msg_3": "K intenzite sa priráta aj hodnota tvojej zbrane. Vyskúšaj si zaútočiť na maketu Skautky."
    },
    "SCOUT_DUMMY": {
        "initial_msg": "Klikni na polovicu karty, na ktorej je \"ÚTOK\".",
        "case_success": "",
        "case_failure": "",
        "type": "Skautka_dummy"
    },
    "TUTORIAL_9": {
        "initial_msg": "V SPORE však môžeš aj robiť manévre výberom polovice karty s OPATRNOSŤOU, na ktorej svieti \"ČIN\".  Ak po výbere tejto karty vyhráš výmenu (hodíš viac, ako súper), zvýši sa tvoja VÝHODA. Tá ti až do konca SPORU poskytuje bonus k hodu.",
        "case_success": "",
        "case_failure": "",
        "choice_A": "Pokračovať.",
        "case_A": [
            "SCOUT_DUMMY_0",
            "TUTORIAL_10"
        ],
        "choice_B": "Preskočiť tutoriál.",
        "case_B": "START",
        "initial_msg_1": "Ak zlyháš a nepriateľ ťa zasiahne počas manévru, zvýšenie stresu, ktoré ti spôsobí, bude stlmené tvojou OPATRNOSŤOU. (Pozor na kartu BEZHLAVO! Tá má \"neopatrnosť\" a súperov útok ešte zosilní, ak ťa trafí.)"
    },
    "SCOUT_DUMMY_0": {
        "initial_msg": "Vyskúšaj v súboji použiť ČIN.",
        "case_success": "",
        "case_failure": "",
        "type": "Skautka_dummy"
    },
    "TUTORIAL_10": {
        "initial_msg": "V hre môžeš čeliť nepriateľom. Vtedy nastane SPOR.",
        "case_success": "",
        "case_failure": "",
        "choice_A": "Pokračovať.",
        "case_A": "TUTORIAL_11",
        "choice_B": "Preskočiť tutoriál.",
        "case_B": "START",
        "initial_msg_1": "Pri spore môžeš použiť aj dolnú stranu kariet. Môžeš si ich otočiť tlačidlom ↺. Otočenie je čisto vizuálne, nemá vplyv na hru.",
        "initial_msg_2": "Na tejto strane kariet je namiesto opatrnosti INTENZITA. Ide o hodnotu, ktorá zvýši súperovi stres, ak ho trafíš. A to, či ho trafíš, určuje vzájomný hod kockami MOTIVÁCIE. Kto hodí viac, ten trafil.",
        "initial_msg_3": "K intenzite sa priráta aj hodnota tvojej zbrane. Vyskúšaj si zaútočiť na maketu Skautky."
    },
    "TUTORIAL_11": {
        "initial_msg": "V hre môžeš čeliť nepriateľom. Vtedy nastane SPOR.",
        "case_success": "",
        "case_failure": "",
        "choice_A": "Pokračovať.",
        "case_A": "TUTORIAL_11",
        "choice_B": "Preskočiť tutoriál.",
        "case_B": "START",
        "initial_msg_1": "Pri spore môžeš použiť aj dolnú stranu kariet. Môžeš si ich otočiť tlačidlom ↺. Otočenie je čisto vizuálne, nemá vplyv na hru.",
        "initial_msg_2": "Na tejto strane kariet je namiesto opatrnosti INTENZITA. Ide o hodnotu, ktorá zvýši súperovi stres, ak ho trafíš. A to, či ho trafíš, určuje vzájomný hod kockami MOTIVÁCIE. Kto hodí viac, ten trafil.",
        "initial_msg_3": "K intenzite sa priráta aj hodnota tvojej zbrane. Vyskúšaj si zaútočiť na maketu Skautky."
    },
    "LAYOUT": {
        "GAME_OVER": {
            "x": 12695,
            "y": 1233
        },
        "DISTRACT_PREDATOR": {
            "x": 8749,
            "y": 1996
        },
        "WRECKS_PREDATOR_2": {
            "x": 8745,
            "y": 1698
        },
        "Predátorka_2": {
            "x": 8357,
            "y": 1744
        },
        "WRECKS_PREDATOR": {
            "x": 8340,
            "y": 1988
        },
        "WRECKS": {
            "x": 9067,
            "y": 1840
        },
        "BASEMENT_PREDATOR_2": {
            "x": 8074,
            "y": 2608
        },
        "Predátorka_1": {
            "x": 8505,
            "y": 2474
        },
        "BASEMENT_PREDATOR": {
            "x": 8784,
            "y": 2391
        },
        "CAR_3": {
            "x": 12309,
            "y": 1264
        },
        "CAR_2": {
            "x": 10066,
            "y": 3299
        },
        "CITY_2": {
            "x": 9149,
            "y": 2755
        },
        "IN_BASEMENT": {
            "x": 8665,
            "y": 2802
        },
        "Skautka_2": {
            "x": 8726,
            "y": 3032
        },
        "BASEMENT_DISTRACT": {
            "x": 8107,
            "y": 3254
        },
        "BASEMENT_ENCOUNTER": {
            "x": 8616,
            "y": 3353
        },
        "EXPLORE_BASEMENT": {
            "x": 9098,
            "y": 3290
        },
        "BASEMENT_ENTRANCE": {
            "x": 9411,
            "y": 3028
        },
        "CITY": {
            "x": 9665,
            "y": 2654
        },
        "Skautka_1": {
            "x": 10317,
            "y": 2387
        },
        "SNEAK": {
            "x": 9913,
            "y": 2416
        },
        "CAR": {
            "x": 10586,
            "y": 2680
        },
        "TEST": {
            "x": 2483,
            "y": 1383
        },
        "TEST2": {
            "x": 2483,
            "y": 1383
        },
        "START": {
            "x": 11101,
            "y": 2446
        },
        "CITY_0": {
            "x": 10175,
            "y": 2697
        },
        "LOOK_AROUND": {
            "x": 10575,
            "y": 2903
        },
        "TOWER_0": {
            "x": 10693,
            "y": 3434
        },
        "WALK_0": {
            "x": 11426,
            "y": 3024
        },
        "FOREST_PATH": {
            "x": 9761,
            "y": 3708
        },
        "SLOPE": {
            "x": 10969,
            "y": 3747
        },
        "CAR_1": {
            "x": 10366,
            "y": 3150
        },
        "WALK_1": {
            "x": 12159,
            "y": 3272
        },
        "TOWER_1": {
            "x": 11746,
            "y": 4417
        },
        "FOREST_PATH_0": {
            "x": 10303,
            "y": 4017
        },
        "SHACK_0": {
            "x": 8946,
            "y": 4285
        },
        "FOREST_PATH_SNEAK": {
            "x": 10510,
            "y": 3771
        },
        "PURITAN_D_0": {
            "x": 10716,
            "y": 4279
        },
        "PURITÁN_1": {
            "x": 10804,
            "y": 4549
        },
        "PURITAN_LIE": {
            "x": 11569,
            "y": 4947
        },
        "PURITAN_THREATEN": {
            "x": 11005,
            "y": 4380
        },
        "PURITAN_CONVINCE": {
            "x": 10485,
            "y": 4839
        },
        "PURITAN_DONT_CONVINCE": {
            "x": 10972,
            "y": 5156
        },
        "FOREST_PATH_1": {
            "x": 9891,
            "y": 4811
        },
        "PURITÁN_2": {
            "x": 8185,
            "y": 2896
        },
        "FOREST_PATH_2": {
            "x": 11054,
            "y": 4656
        },
        "CLIFF": {
            "x": 11078,
            "y": 3504
        },
        "CLIFF_CLIMB": {
            "x": 11216,
            "y": 3874
        },
        "GENERATOR": {
            "x": 12103,
            "y": 4466
        },
        "SUCK": {
            "x": 12322,
            "y": 4194
        },
        "CAR_5": {
            "x": 11225,
            "y": 3194
        },
        "SHACK_LOOK_AROUND": {
            "x": 8164,
            "y": 4765
        },
        "SHACK_DOOR_BREAK": {
            "x": 8844,
            "y": 4711
        },
        "SHACK_WINDOW": {
            "x": 9245,
            "y": 4554
        },
        "SHACK_CELLAR": {
            "x": 8048,
            "y": 5755
        },
        "SHACK_1": {
            "x": 9125,
            "y": 4886
        },
        "SHACK_CELLAR_0": {
            "x": 7694,
            "y": 5589
        },
        "UNLOCK_CELLAR": {
            "x": 9555,
            "y": 5093
        },
        "SHACK_ATTIC": {
            "x": 9180,
            "y": 5286
        },
        "SHACK_2": {
            "x": 9577,
            "y": 5468
        },
        "SHACK_EXPLORE": {
            "x": 8620,
            "y": 5350
        },
        "SHACK_EXPLORE_2": {
            "x": 8664,
            "y": 4993
        },
        "DEAD_LETTERS": {
            "x": 9409,
            "y": 5688
        },
        "DEAD_LETTERS_0": {
            "x": 9514,
            "y": 5892
        },
        "DEAD_LETTERS_1": {
            "x": 9720,
            "y": 6030
        },
        "DEAD_LETTERS_2": {
            "x": 9986,
            "y": 6128
        },
        "DEAD_LETTERS_3": {
            "x": 10531,
            "y": 6057
        },
        "DEAD_LETTERS_4": {
            "x": 10802,
            "y": 5934
        },
        "DEAD_LETTERS_5": {
            "x": 11030,
            "y": 5807
        },
        "DEAD_LETTERS_6": {
            "x": 10259,
            "y": 6128
        },
        "WRECKS_0": {
            "x": 9174,
            "y": 2313
        },
        "NO_CONTAINER": {
            "x": 11940,
            "y": 1442
        },
        "NO_HOSE": {
            "x": 11724,
            "y": 1569
        },
        "NO_HOSE_NO_CONTAINER": {
            "x": 11549,
            "y": 1690
        },
        "WALK_3": {
            "x": 12648,
            "y": 3062
        },
        "WALK_4": {
            "x": 12875,
            "y": 2944
        },
        "SKAUTKA_3": {
            "x": 12927,
            "y": 3302
        },
        "PREDÁTORKA_2": {
            "x": 12682,
            "y": 3339
        },
        "SKAUTKA_0": {
            "x": 12202,
            "y": 3501
        },
        "WALK_2": {
            "x": 12459,
            "y": 3208
        },
        "PREDÁTORKA_0": {
            "x": 12498,
            "y": 3381
        },
        "WALK_5": {
            "x": 13113,
            "y": 2763
        },
        "PREDÁTORKA_3": {
            "x": 13020,
            "y": 3144
        },
        "PREDÁTORKA_4": {
            "x": 13240,
            "y": 3143
        },
        "PREDÁTORKA_5": {
            "x": 13269,
            "y": 2988
        },
        "GAME_FINISHED": {
            "x": 13353,
            "y": 2630
        },
        "CLIFF_CLIMB_0": {
            "x": 11371,
            "y": 3693
        },
        "TOWER_2": {
            "x": 11508,
            "y": 4209
        },
        "PURITAN_ESCAPE": {
            "x": 10301,
            "y": 4335
        },
        "TRACK": {
            "x": 13222,
            "y": 4119
        },
        "LAKE": {
            "x": 13554,
            "y": 4283
        },
        "BUNKER": {
            "x": 13868,
            "y": 4442
        },
        "BUNKER_0": {
            "x": 14275,
            "y": 4459
        },
        "DIVE": {
            "x": 14200,
            "y": 4742
        },
        "DIVE_0": {
            "x": 14593,
            "y": 4600
        },
        "DIVE_4": {
            "x": 14492,
            "y": 4153
        },
        "BUNKER_1": {
            "x": 14944,
            "y": 4801
        },
        "TUTORIAL": {
            "x": 16138,
            "y": 41
        },
        "TUTORIAL_0": {
            "x": 16466,
            "y": 120
        },
        "TUTORIAL_1": {
            "x": 16727,
            "y": 239
        },
        "TUTORIAL_2": {
            "x": 16957,
            "y": 323
        },
        "TUTORIAL_3": {
            "x": 17236,
            "y": 419
        },
        "TUTORIAL_4": {
            "x": 17474,
            "y": 524
        },
        "TUTORIAL_5": {
            "x": 17689,
            "y": 346
        },
        "TUTORIAL_6": {
            "x": 17721,
            "y": 618
        },
        "TUTORIAL_7": {
            "x": 18096,
            "y": 504
        },
        "TUTORIAL_8": {
            "x": 17961,
            "y": 716
        },
        "SCOUT_DUMMY": {
            "x": 18479,
            "y": 603
        },
        "TUTORIAL_9": {
            "x": 18188,
            "y": 815
        },
        "SCOUT_DUMMY_0": {
            "x": 18709,
            "y": 756
        },
        "TUTORIAL_10": {
            "x": 18414,
            "y": 911
        },
        "TUTORIAL_11": {
            "x": 18688,
            "y": 1027
        }
    },
    "ACTIVE": {
        "BASEMENT_DISTRACT": true,
        "BASEMENT_ENCOUNTER": true,
        "BASEMENT_ENTRANCE": true,
        "BASEMENT_PREDATOR": true,
        "BASEMENT_PREDATOR_2": true,
        "CAR": true,
        "CAR_1": true,
        "CAR_2": true,
        "CAR_3": true,
        "CAR_5": true,
        "CITY": false,
        "CITY_0": true,
        "CITY_2": true,
        "CLIFF": true,
        "CLIFF_CLIMB": true,
        "DISTRACT_PREDATOR": true,
        "EXPLORE_BASEMENT": true,
        "FOREST_PATH": true,
        "FOREST_PATH_0": true,
        "FOREST_PATH_1": true,
        "FOREST_PATH_2": true,
        "FOREST_PATH_SNEAK": true,
        "GAME_OVER": true,
        "GENERATOR": true,
        "IN_BASEMENT": true,
        "LOOK_AROUND": true,
        "PURITAN_CONVINCE": true,
        "PURITAN_D_0": true,
        "PURITAN_DONT_CONVINCE": true,
        "PURITAN_LIE": true,
        "PURITAN_THREATEN": true,
        "PURITÁN_1": true,
        "PURITÁN_2": true,
        "Predátorka_1": true,
        "Predátorka_2": true,
        "SHACK_0": true,
        "SHACK_1": true,
        "SHACK_CELLAR": false,
        "SHACK_DOOR_BREAK": true,
        "SHACK_LOOK_AROUND": true,
        "SHACK_WINDOW": true,
        "SNEAK": true,
        "Skautka_1": true,
        "Skautka_2": true,
        "SLOPE": true,
        "START": true,
        "SUCK": false,
        "TOWER_0": true,
        "TOWER_1": false,
        "WALK_0": true,
        "WALK_1": true,
        "WRECKS": false,
        "WRECKS_PREDATOR": true,
        "WRECKS_PREDATOR_2": true,
        "SHACK_CELLAR_0": true,
        "UNLOCK_CELLAR": true,
        "SHACK_ATTIC": true,
        "SHACK_EXPLORE": true,
        "SHACK_EXPLORE_2": true,
        "SHACK_2": false,
        "DEAD_LETTERS": true,
        "DEAD_LETTERS_0": true,
        "DEAD_LETTERS_1": true,
        "DEAD_LETTERS_2": true,
        "DEAD_LETTERS_3": true,
        "DEAD_LETTERS_4": true,
        "DEAD_LETTERS_5": true,
        "DEAD_LETTERS_6": true,
        "WRECKS_0": true,
        "NO_CONTAINER": false,
        "NO_HOSE": false,
        "NO_HOSE_NO_CONTAINER": true,
        "WALK_3": true,
        "WALK_4": true,
        "SKAUTKA_3": true,
        "SKAUTKA_0": true,
        "PREDÁTORKA_2": true,
        "WALK_5": true,
        "PREDÁTORKA_5": true,
        "PREDÁTORKA_4": true,
        "PREDÁTORKA_3": true,
        "WALK_2": true,
        "PREDÁTORKA_0": true,
        "GAME_FINISHED": true,
        "CLIFF_CLIMB_0": false,
        "TOWER_2": true,
        "PURITAN_ESCAPE": true,
        "TRACK": true,
        "TEST": true,
        "LAKE": true,
        "TEST2": true,
        "BUNKER": true,
        "BUNKER_0": true,
        "BUNKER_1": true,
        "DIVE": true,
        "DIVE_0": false,
        "DIVE_4": false,
        "TUTORIAL": true,
        "TUTORIAL_0": true,
        "TUTORIAL_1": true,
        "TUTORIAL_2": true,
        "TUTORIAL_3": true,
        "TUTORIAL_4": true,
        "TUTORIAL_5": true,
        "TUTORIAL_6": true,
        "TUTORIAL_7": true,
        "TUTORIAL_8": true,
        "SCOUT_DUMMY": true,
        "TUTORIAL_9": true,
        "SCOUT_DUMMY_0": true,
        "TUTORIAL_10": true,
        "TUTORIAL_11": true
    }
}